Calculadora/rtl/cores/Divisor/div_control.v
module div_control #(

// Establecimiento de los estados como parámetros

    parameter START = 3'b000,
    parameter CHECK1 = 3'b001,
    parameter LOAD = 3'b010,
    parameter DEC_SHIFT = 3'b011,
    parameter CHECK2 = 3'b100,
    parameter SHIFT2 = 3'b101,
    parameter FINISH = 3'b110

) (

    input clk,
    input init,
    input residuo_MSB,
    input zero,
    input rst,


    output reg LD0,
    output reg LD1,
    output reg SH0,
    output reg SH1,
    output reg DECI,
    output reg done

);


// Maquina de estados: lógica de transición

    reg [2:0] current_state;
    reg [4:0] count;


    always @(posedge clk) begin

        if(rst) begin
            current_state = START;
            
        end else begin

            case (current_state)
                START: begin
                    if (init) begin
                        current_state = CHECK1;
                        count = 0;
                    end else begin
                        current_state = START;
                    end
                end

                CHECK1: begin
                    if(residuo_MSB) begin
                        current_state = DEC_SHIFT;
                    end else begin 
                        current_state = LOAD;
                    end
                end

                LOAD: begin
                    current_state = DEC_SHIFT;
                end

                DEC_SHIFT: begin
                    current_state = CHECK2;
                end

                CHECK2: begin
                    if (zero) begin
                        current_state = FINISH;
                    end else begin
                        current_state = SHIFT2;
                    end
                end

                SHIFT2: begin
                    current_state = CHECK1;
                end

                FINISH: begin
                    count = count + 1;
                    current_state = (count>31) ? START : FINISH ;
                end

                default: current_state = START;
            
            endcase
        end
    end

// Salidas según el estado

always @(*) begin
    LD0  = 1'b0;
    LD1  = 1'b0;
    SH0  = 1'b0;
    SH1  = 1'b0;
    DECI = 1'b0;
    done = 1'b0;

    case (current_state)

        START: begin
            LD0  <= 1;
            LD1  <= 0;
            SH0  <= 0;
            SH1  <= 0;
            DECI <= 0;
            done <= 0;
        end

        CHECK1: begin
            LD0  <= 0;
            LD1  <= 0;
            SH0  <= 0;
            SH1  <= 0;
            DECI <= 0;
            done <= 0;
        end

        LOAD: begin
            LD0  <= 0;
            LD1  <= 1;
            SH0  <= 0;
            SH1  <= 0;
            DECI <= 0;
            done <= 0;
        end


        DEC_SHIFT: begin
            LD0  <= 0;
            LD1  <= 0;
            SH0  <= 1;
            SH1  <= 0;
            DECI <= 1;
            done <= 0;
        end 

        CHECK2: begin
            LD0  <= 0;
            LD1  <= 0;
            SH0  <= 0;
            SH1  <= 0;
            DECI <= 0;
            done <= 0;
        end   

        SHIFT2: begin
            LD0  <= 0;
            LD1  <= 0;
            SH0  <= 0;
            SH1  <= 1;
            DECI <= 0;
            done <= 0;
        end

        FINISH: begin
            LD0  <= 0;
            LD1  <= 0;
            SH0  <= 0;
            SH1  <= 0;
            DECI <= 0;
            done <= 1;
        end

    default: begin
            LD0  <= 0;
            LD1  <= 0;
            SH0  <= 0;
            SH1  <= 0;
            DECI <= 0;
            done <= 0;
       end

    endcase
end

//Bloque que asigna codigos ASCII a las señales

`ifdef BENCH
reg [8*40-12:1] state_name;
always @(*) begin
    case (current_state)
        START: state_name <= "START";
        CHECK1: state_name <= "CHECK1";
        LOAD: state_name <= "LOAD";
        DEC_SHIFT: state_name <= "DEC_SHIFT";
        CHECK2: state_name <= "CHECK2";
        SHIFT2: state_name <= "SHIFT2";
        FINISH: state_name <= "FINISH";
    endcase
end
`endif



endmodule

Calculadora/rtl/cores/Divisor/lsr_cociente.v
module lsr_cociente (
    input clk,
    input LD1,
    input SH1,
    input LD0,

    output reg [7:0] out_cociente
    
);

always @(negedge clk) begin
    if(LD1) begin
        out_cociente[0] <= 1;
    end else if (SH1) begin
        out_cociente <= out_cociente << 1; 
    end else if (LD0) begin
        out_cociente <= 7'b0;
    end
end
   
    
endmodule

Calculadora/rtl/cores/Divisor/sum_res_comp2.v
module sum_res_comp2 (
    input [7:0] in_B,
    input [7:0] in_vAux,

    output reg [7:0] residuo,
    output reg residuo_MSB
);

always @(*) begin
    residuo <= in_vAux - in_B;
    residuo_MSB <= residuo[7];
end
    
endmodule

Calculadora/rtl/cores/Divisor/contador_dec.v
module contador_dec #(
    parameter width = 4
) (

    input clk,
    input LD0,
    input DECI,

    output reg zero

);

reg [7:0] out;

    always @(negedge clk) begin
        if (LD0) begin
            out <= 8;
        end else if (DECI) begin
            out <= out - 1;
        end

        assign zero = (out == 0);     //Señal que se activa una vez el contador llega a 0
    end



    
endmodule

Calculadora/rtl/cores/Divisor/lsr_vAux.v
module lsr_vAux (
    input clk,
    input SH0,
    input LD0,
    input LD1,
    input SH1,
    input [7:0] in_A,
    input [7:0] residuo,


    output reg [7:0] out_vAux
    
);

always @(negedge clk) begin
    if(LD0) begin
        out_vAux <= 8'b0;
    end
    if (LD1) begin
        out_vAux <= residuo; 
    end
    if (SH0) begin
        out_vAux <= out_vAux << 1;
    end
    if (SH1) begin
        out_vAux[0] <= in_A[7];
    end
end
   
    
    
endmodule

Calculadora/rtl/cores/Divisor/Breg.v
module Breg (
    input clk,
    input LD0,
    input [7:0] in_B,
    output reg [7:0] out_B

);
    always @(negedge clk) begin
        if (LD0) begin
            out_B = in_B;
        end
    end

endmodule

Calculadora/rtl/cores/Divisor/lsr_A.v
module lsr_A (
    input clk,
    input LD0,
    input SH0,
    input [7:0] in_A,

    output reg [7:0] out_sh_A
);

always @(negedge clk) begin
    if(LD0) begin
        out_sh_A = in_A;
    end else if (SH0) begin
        out_sh_A = out_sh_A << 1; 
    end 
end
   
    
endmodule

Calculadora/rtl/cores/Divisor/div_top.v
module div_top (

    input clk,
    input init,
    input rst,
    input [7:0] A,
    input [7:0] B,

    output [7:0] residuo,
    output [7:0] cociente,
    output done

);

wire [7:0] w_out_A;
wire [7:0] w_out_B;
wire [7:0] w_out_vAux;
wire w_residuo_MSB;
wire [7:0] w_residuo;

wire load;
wire loadResiduo;
wire shift_cociente;
wire dec_I;

wire w_zero;

assign residuo = w_residuo;


//Organización de módulos dentro del multipllicador



lsr_A Areg ( 
    .clk (clk), .LD0 (load), .SH0 (shift), .in_A (A), // Entradas
    .out_sh_A (w_out_A) //Salidas
    
    );

Breg Breg ( 
    .clk (clk), .LD0 (load), .in_B (B), // Entradas
    .out_B (w_out_B) //Salidas
    
    );

lsr_vAux vAuxReg  ( 
    .clk (clk), .LD0 (load), .LD1 (loadResiduo), .SH0 (shift), .SH1 (shift_cociente), .in_A (w_out_A), .residuo (w_residuo), // Entradas
    .out_vAux (w_out_vAux) //Salidas
    
    );

contador_dec cont0 ( 
    .clk (clk), .LD0 (load), .DECI (dec_I), // Entradas
    .zero (w_zero) //Salidas
    
    );

sum_res_comp2 sum_res_comp20 ( 
    .in_B (w_out_B), .in_vAux (w_out_vAux), // Entradas
    .residuo (w_residuo), .residuo_MSB (w_residuo_MSB) //Salidas
    
    );

lsr_cociente cocienteReg ( 
    .clk (clk), .LD0 (load), .LD1 (loadResiduo), .SH1 (shift_cociente),// Entradas
    .out_cociente (cociente) //Salidas
    
    );

div_control control ( 
    .clk (clk), .init (init), .residuo_MSB (w_residuo_MSB), .zero (w_zero), .rst (rst), // Entradas
    .done (done), .LD0 (load), .LD1 (loadResiduo), .SH0 (shift), .SH1 (shift_cociente), .DECI (dec_I) //Salidas
    
    );



endmodule

Calculadora/rtl/cores/Divisor/div_TB.v
`timescale 10ns / 10ns
`define SIMULATION

module div_TB;


reg clk;
reg init; 
reg rst;
reg [7:0] A; 
reg [7:0] B; 

wire [7:0] cociente;
wire [7:0] residuo;
wire done;

// Inicialización del modulo

div_top uut ( //Unit under test
    .clk (clk), .init (init), .rst (rst), .A (A), .B (B), // Entradas

    .residuo (residuo), .cociente (cociente), .done (done) // Salidas
    
    );


initial clk = 0; 
always #1 clk = ~clk;


initial begin
    $dumpfile("div_TB.vcd");
    $dumpvars(-1, div_TB);

    $monitor("t=%0t A=0x%h B=0x%h cociente=0x%h residuo=0x%h done=%b", $time, A, B, cociente, residuo, done);
end


initial begin

    @(negedge clk);
    @(posedge clk);

    A = 0;
    B = 0;
    init = 0;
    rst = 0;

    @(negedge clk);
    @(posedge clk);

    A = 8'b01000011;
    B = 8'b00001001;

    @(negedge clk);
    @(posedge clk);

    rst = 1;

    @(negedge clk);
    @(posedge clk);

    rst = 0;

    @(negedge clk);
    @(posedge clk);
    
    init = 1;

    @(negedge clk);
    @(posedge clk);

    init = 0;

    wait(done == 1);
    #1000;

    $finish;
end



endmodule

Calculadora/rtl/cores/Divisor/div_TB.vcd
$date
	Tue May 19 07:52:04 2026
$end
$version
	Icarus Verilog
$end
$timescale
	10ns
$end
$scope module div_TB $end
$var wire 8 ! residuo [7:0] $end
$var wire 1 " done $end
$var wire 8 # cociente [7:0] $end
$var reg 8 $ A [7:0] $end
$var reg 8 % B [7:0] $end
$var reg 1 & clk $end
$var reg 1 ' init $end
$var reg 1 ( rst $end
$scope module uut $end
$var wire 8 ) A [7:0] $end
$var wire 8 * B [7:0] $end
$var wire 1 & clk $end
$var wire 1 ' init $end
$var wire 8 + residuo [7:0] $end
$var wire 1 ( rst $end
$var wire 1 , w_zero $end
$var wire 1 - w_residuo_MSB $end
$var wire 8 . w_residuo [7:0] $end
$var wire 8 / w_out_vAux [7:0] $end
$var wire 8 0 w_out_B [7:0] $end
$var wire 8 1 w_out_A [7:0] $end
$var wire 1 2 shift_cociente $end
$var wire 1 3 shift $end
$var wire 1 4 loadResiduo $end
$var wire 1 5 load $end
$var wire 1 " done $end
$var wire 1 6 dec_I $end
$var wire 8 7 cociente [7:0] $end
$scope module Areg $end
$var wire 1 & clk $end
$var wire 8 8 in_A [7:0] $end
$var wire 1 3 SH0 $end
$var wire 1 5 LD0 $end
$var reg 8 9 out_sh_A [7:0] $end
$upscope $end
$scope module Breg $end
$var wire 1 & clk $end
$var wire 8 : in_B [7:0] $end
$var wire 1 5 LD0 $end
$var reg 8 ; out_B [7:0] $end
$upscope $end
$scope module cocienteReg $end
$var wire 1 & clk $end
$var wire 1 2 SH1 $end
$var wire 1 4 LD1 $end
$var wire 1 5 LD0 $end
$var reg 8 < out_cociente [7:0] $end
$upscope $end
$scope module cont0 $end
$var wire 1 & clk $end
$var wire 1 5 LD0 $end
$var wire 1 6 DECI $end
$var parameter 32 = width $end
$var reg 8 > out [7:0] $end
$var reg 1 , zero $end
$upscope $end
$scope module control $end
$var wire 1 & clk $end
$var wire 1 ' init $end
$var wire 1 ( rst $end
$var wire 1 , zero $end
$var wire 1 - residuo_MSB $end
$var parameter 3 ? CHECK1 $end
$var parameter 3 @ CHECK2 $end
$var parameter 3 A DEC_SHIFT $end
$var parameter 3 B FINISH $end
$var parameter 3 C LOAD $end
$var parameter 3 D SHIFT2 $end
$var parameter 3 E START $end
$var reg 1 6 DECI $end
$var reg 1 5 LD0 $end
$var reg 1 4 LD1 $end
$var reg 1 3 SH0 $end
$var reg 1 2 SH1 $end
$var reg 5 F count [4:0] $end
$var reg 3 G current_state [2:0] $end
$var reg 1 " done $end
$var reg 308 H state_name [308:1] $end
$upscope $end
$scope module sum_res_comp20 $end
$var wire 8 I in_B [7:0] $end
$var wire 8 J in_vAux [7:0] $end
$var reg 8 K residuo [7:0] $end
$var reg 1 - residuo_MSB $end
$upscope $end
$scope module vAuxReg $end
$var wire 1 5 LD0 $end
$var wire 1 4 LD1 $end
$var wire 1 3 SH0 $end
$var wire 1 2 SH1 $end
$var wire 1 & clk $end
$var wire 8 L in_A [7:0] $end
$var wire 8 M residuo [7:0] $end
$var reg 8 N out_vAux [7:0] $end
$upscope $end
$upscope $end
$upscope $end
$enddefinitions $end
$comment Show the parameter values. $end
$dumpall
b0 E
b101 D
b10 C
b110 B
b11 A
b100 @
b1 ?
b100 =
$end
#0
$dumpvars
bx N
bx M
bx L
bx K
bx J
bx I
bx H
bx G
bx F
bx >
bx <
bx ;
bx :
bx 9
bx 8
bx 7
x6
x5
x4
x3
x2
bx 1
bx 0
bx /
bx .
x-
x,
bx +
bx *
bx )
x(
x'
0&
bx %
bx $
bx #
x"
bx !
$end
#1
b101001101010100010000010101001001010100 H
0"
06
02
03
04
15
b0 G
1&
#2
b0 #
b0 7
b0 <
b1000 >
b0 /
b0 J
b0 N
0&
#3
0(
0'
b0 %
b0 *
b0 :
b0 $
b0 )
b0 8
1&
#4
0-
b0 !
b0 +
b0 .
b0 K
b0 M
b0 1
b0 9
b0 L
b0 0
b0 ;
b0 I
0,
0&
#5
b1001 %
b1001 *
b1001 :
b1000011 $
b1000011 )
b1000011 8
1&
#6
1-
b11110111 !
b11110111 +
b11110111 .
b11110111 K
b11110111 M
b1001 0
b1001 ;
b1001 I
b1000011 1
b1000011 9
b1000011 L
0&
#7
1(
1&
#8
0&
#9
0(
1&
#10
0&
#11
b10000110100100001000101010000110100101100110001 H
05
b1 G
1'
1&
#12
0&
#13
b10001000100010101000011010111110101001101001000010010010100011001010100 H
16
13
b11 G
0'
1&
#14
b111 >
b10000110 1
b10000110 9
b10000110 L
0&
#15
b10000110100100001000101010000110100101100110010 H
06
03
b100 G
1&
#16
0&
#17
b10100110100100001001001010001100101010000110010 H
12
b101 G
1&
#18
b11111000 !
b11111000 +
b11111000 .
b11111000 K
b11111000 M
b1 /
b1 J
b1 N
0&
#19
b10000110100100001000101010000110100101100110001 H
02
b1 G
1&
#20
0&
#21
b10001000100010101000011010111110101001101001000010010010100011001010100 H
16
13
b11 G
1&
#22
b11111001 !
b11111001 +
b11111001 .
b11111001 K
b11111001 M
b110 >
b10 /
b10 J
b10 N
b1100 1
b1100 9
b1100 L
0&
#23
b10000110100100001000101010000110100101100110010 H
06
03
b100 G
1&
#24
0&
#25
b10100110100100001001001010001100101010000110010 H
12
b101 G
1&
#26
0&
#27
b10000110100100001000101010000110100101100110001 H
02
b1 G
1&
#28
0&
#29
b10001000100010101000011010111110101001101001000010010010100011001010100 H
16
13
b11 G
1&
#30
b11111011 !
b11111011 +
b11111011 .
b11111011 K
b11111011 M
b101 >
b100 /
b100 J
b100 N
b11000 1
b11000 9
b11000 L
0&
#31
b10000110100100001000101010000110100101100110010 H
06
03
b100 G
1&
#32
0&
#33
b10100110100100001001001010001100101010000110010 H
12
b101 G
1&
#34
0&
#35
b10000110100100001000101010000110100101100110001 H
02
b1 G
1&
#36
0&
#37
b10001000100010101000011010111110101001101001000010010010100011001010100 H
16
13
b11 G
1&
#38
b11111111 !
b11111111 +
b11111111 .
b11111111 K
b11111111 M
b100 >
b1000 /
b1000 J
b1000 N
b110000 1
b110000 9
b110000 L
0&
#39
b10000110100100001000101010000110100101100110010 H
06
03
b100 G
1&
#40
0&
#41
b10100110100100001001001010001100101010000110010 H
12
b101 G
1&
#42
0&
#43
b10000110100100001000101010000110100101100110001 H
02
b1 G
1&
#44
0&
#45
b10001000100010101000011010111110101001101001000010010010100011001010100 H
16
13
b11 G
1&
#46
0-
b111 !
b111 +
b111 .
b111 K
b111 M
b11 >
b10000 /
b10000 J
b10000 N
b1100000 1
b1100000 9
b1100000 L
0&
#47
b10000110100100001000101010000110100101100110010 H
06
03
b100 G
1&
#48
0&
#49
b10100110100100001001001010001100101010000110010 H
12
b101 G
1&
#50
0&
#51
b10000110100100001000101010000110100101100110001 H
02
b1 G
1&
#52
0&
#53
b1001100010011110100000101000100 H
14
b10 G
1&
#54
1-
b11111110 !
b11111110 +
b11111110 .
b11111110 K
b11111110 M
b1 #
b1 7
b1 <
b111 /
b111 J
b111 N
0&
#55
16
13
b10001000100010101000011010111110101001101001000010010010100011001010100 H
04
b11 G
1&
#56
0-
b101 !
b101 +
b101 .
b101 K
b101 M
b1110 /
b1110 J
b1110 N
b10 >
b11000000 1
b11000000 9
b11000000 L
0&
#57
b10000110100100001000101010000110100101100110010 H
06
03
b100 G
1&
#58
0&
#59
12
b10100110100100001001001010001100101010000110010 H
b101 G
1&
#60
b110 !
b110 +
b110 .
b110 K
b110 M
b1111 /
b1111 J
b1111 N
b10 #
b10 7
b10 <
0&
#61
b10000110100100001000101010000110100101100110001 H
02
b1 G
1&
#62
0&
#63
14
b1001100010011110100000101000100 H
b10 G
1&
#64
1-
b11111101 !
b11111101 +
b11111101 .
b11111101 K
b11111101 M
b110 /
b110 J
b110 N
b11 #
b11 7
b11 <
0&
#65
b10001000100010101000011010111110101001101001000010010010100011001010100 H
16
13
04
b11 G
1&
#66
0-
b11 !
b11 +
b11 .
b11 K
b11 M
b1 >
b1100 /
b1100 J
b1100 N
b10000000 1
b10000000 9
b10000000 L
0&
#67
b10000110100100001000101010000110100101100110010 H
06
03
b100 G
1&
#68
0&
#69
b10100110100100001001001010001100101010000110010 H
12
b101 G
1&
#70
b100 !
b100 +
b100 .
b100 K
b100 M
b110 #
b110 7
b110 <
b1101 /
b1101 J
b1101 N
0&
#71
b10000110100100001000101010000110100101100110001 H
02
b1 G
1&
#72
0&
#73
b1001100010011110100000101000100 H
14
b10 G
1&
#74
1-
b11111011 !
b11111011 +
b11111011 .
b11111011 K
b11111011 M
b111 #
b111 7
b111 <
b100 /
b100 J
b100 N
0&
#75
16
13
b10001000100010101000011010111110101001101001000010010010100011001010100 H
04
b11 G
1&
#76
b11111111 !
b11111111 +
b11111111 .
b11111111 K
b11111111 M
b1000 /
b1000 J
b1000 N
b0 >
b0 1
b0 9
b0 L
0&
#77
b10000110100100001000101010000110100101100110010 H
06
03
b100 G
1&
#78
1,
0&
#79
1"
b10001100100100101001110010010010101001101001000 H
b110 G
1&
#80
0&
#81
0"
bx0 G
1&
#82
0&
#83
15
b101001101010100010000010101001001010100 H
b0 G
1&
#84
b11110111 !
b11110111 +
b11110111 .
b11110111 K
b11110111 M
b0 /
b0 J
b0 N
b1000 >
b0 #
b0 7
b0 <
b1000011 1
b1000011 9
b1000011 L
0&
#85
1&
#86
0,
0&
