Calculadora/rtl/cores/bin2bcd/bin2bcd_control.v
module bin2bcd_control #(

// Establecimiento de los estados como parámetros

    parameter START = 4'b0000,
    parameter SHIFT = 4'b0001,
    parameter CHECK = 4'b0010,
    parameter LOAD_O = 4'b0011,
    parameter LOAD_T = 4'b0100,
    parameter LOAD_H = 4'b0101,
    parameter DEC_I = 4'b0110,
    parameter FCHECK = 4'b0111,
    parameter FINISH = 4'b1000

) (

    input clk,
    input init,
    input rst,
    input O,
    input T,
    input H,
    input Z,

    output reg done,
    output reg LD0,
    output reg LD1,
    output reg LD2,
    output reg LD3,
    output reg DEC,
    output reg SH

);


// Maquina de estados: lógica de transición

    reg [3:0] current_state;
    reg [4:0] count;

    always @(negedge clk) begin

        if(rst) begin
            current_state = START;
            
        end else begin

            case (current_state)
                START: begin
                    if (init) begin
                        current_state = SHIFT;
                        count = 0;
                    end else begin
                        current_state = START;
                    end
                end

                SHIFT: begin
                    current_state = CHECK;
                end

                CHECK: begin
                    if(O) begin
                        current_state = LOAD_O;
                    end else if (T) begin 
                        current_state = LOAD_T;
                    end else if (H) begin 
                        current_state = LOAD_H;
                    end else begin
                        current_state = DEC_I;
                    end
                end

                LOAD_O: begin
                    current_state = DEC_I;
                end

                LOAD_T: begin
                    current_state = DEC_I;
                end

                LOAD_H: begin
                    current_state = DEC_I;
                end  

                DEC_I: begin
                    current_state = FCHECK;
                end            

                FCHECK: begin
                    if (Z) begin
                        current_state = FINISH;
                    end else begin
                        current_state = SHIFT;
                    end
                end

                FINISH: begin
                    count = count + 1;
                    current_state = (count>28) ? START : FINISH ;
                end


                default: current_state = START;
            
            endcase
        end
    end

// Salidas según el estado

always @(*) begin

    case (current_state)

        START: begin
            LD0  <= 1;
            LD1  <= 0;
            LD2  <= 0;
            LD3  <= 0;
            SH   <= 0;
            DEC  <= 0;
            done <= 0;
        end

        SHIFT: begin
            LD0  <= 0;
            LD1  <= 0;
            LD2  <= 0;
            LD3  <= 0;
            SH   <= 1;
            DEC  <= 0;
            done <= 0;
        end

        CHECK: begin
            LD0  <= 0;
            LD1  <= 0;
            LD2  <= 0;
            LD3  <= 0;
            SH   <= 0;
            DEC  <= 0;
            done <= 0;
        end

        LOAD_O: begin
            LD0  <= 0;
            LD1  <= 1;
            LD2  <= 0;
            LD3  <= 0;
            SH   <= 0;
            DEC  <= 0;
            done <= 0;
        end 

        LOAD_T: begin
            LD0  <= 0;
            LD1  <= 0;
            LD2  <= 1;
            LD3  <= 0;
            SH   <= 0;
            DEC  <= 0;
            done <= 0;
        end   

        LOAD_H: begin
            LD0  <= 0;
            LD1  <= 0;
            LD2  <= 0;
            LD3  <= 1;
            SH   <= 0;
            DEC  <= 0;
            done <= 0;
        end 

        DEC_I: begin
            LD0  <= 0;
            LD1  <= 0;
            LD2  <= 0;
            LD3  <= 0;
            SH   <= 0;
            DEC  <= 1;
            done <= 0;
        end

        FCHECK: begin
            LD0  <= 0;
            LD1  <= 0;
            LD2  <= 0;
            LD3  <= 0;
            SH   <= 0;
            DEC  <= 0;
            done <= 0;
        end

        FINISH: begin
            LD0  <= 0;
            LD1  <= 0;
            LD2  <= 0;
            LD3  <= 0;
            SH   <= 0;
            DEC  <= 0;
            done <= 1;
        end

    default: begin
            LD0  <= 0;
            LD1  <= 0;
            LD2  <= 0;
            LD3  <= 0;
            DEC  <= 0;
            SH   <= 0;
            done <= 0;
       end

    endcase
end

//Bloque que asigna codigos ASCII a las señales

`ifdef BENCH
reg [8*40:1] state_name;
always @(*) begin
    case (current_state)
        START: state_name = "START";
        SHIFT: state_name = "SHIFT";
        CHECK: state_name = "CHECK";
        LOAD_O: state_name = "LOAD_O";
        LOAD_T: state_name = "LOAD_T";
        LOAD_H: state_name = "LOAD_H";
        DEC_I: state_name = "DEC_I";
        FCHECK: state_name = "FCHECK";
        FINISH: state_name = "FINISH";
    endcase
end
`endif



endmodule

Calculadora/rtl/cores/bcd2bin/sum_comp2.v
module sum_comp2 (
    input [3:0] in_bcd,

    output reg [3:0] out_bcd
);
    
    always @(*) begin
        out_bcd = in_bcd - 4'b0011;
    end

endmodule

Calculadora/rtl/cores/bcd2bin/contador_dec.v
module contador_dec (

    input clk,
    input LD0,
    input DECI,

    output reg Z

);

reg [7:0] out;

    always @(posedge clk) begin
        if (LD0) begin
            out <= 8;
        end else if (DECI) begin
            out <= out - 1;
        end
        Z = (out == 0); //Señal que se activa una vez el contador llega a 0
    end



    
endmodule

Calculadora/rtl/cores/bcd2bin/comp.v
module comp (
    input [3:0] bcd,

    output reg Y
);

always @(*) begin
    if(bcd >= 8) begin
        Y = 1;
    end else begin
        Y = 0;
    end
end
    
endmodule

Calculadora/rtl/cores/bcd2bin/lsr_A_res.v
module lsr_A_res (

    input clk,
    input [11:0] A_bcd,
    input [3:0] ones_comp2,
    input [3:0] tens_comp2,
    input [3:0] hundreds_comp2,
    input LD0,
    input LD1,
    input LD2,
    input LD3,
    input SH,
    
    output reg [3:0] bcd_ones, 
    output reg [3:0] bcd_tens, 
    output reg [3:0] bcd_hundreds, 
    output reg [7:0] A_bin
);
    
    reg [11:0] temp_A_bcd;

    always @(posedge clk) begin
        if (LD0) begin
            A_bin = 8'b0;
            temp_A_bcd = A_bcd;
        end else if (LD1) begin
            temp_A_bcd[3:0] = ones_comp2;
        end else if (LD2) begin
            temp_A_bcd[7:4] = tens_comp2;
        end else if (LD3) begin
            temp_A_bcd[11:8] = hundreds_comp2;
        end else if (SH) begin
            A_bin = {temp_A_bcd[0],A_bin[7:1]};
            temp_A_bcd = temp_A_bcd >> 1;
        end
        
        bcd_ones = temp_A_bcd[3:0];
        bcd_tens = temp_A_bcd[7:4];
        bcd_hundreds = temp_A_bcd[11:8];
    end

endmodule

Calculadora/rtl/cores/bcd2bin/bcd2bin_top.v
module bcd2bin_top (
    input clk,
    input init,
    input rst,
    input [11:0] A_bcd,

    output [7:0] A_bin,
    output done
);

wire [7:0] w_Abin;
wire [3:0] w_bcd_ones;
wire [3:0] w_bcd_tens;
wire [3:0] w_bcd_hundreds;

wire [3:0] w_ones_comp2;
wire [3:0] w_tens_comp2;
wire [3:0] w_hundreds_comp2;

wire load_reset;
wire load_ones;
wire load_tens;
wire load_hundreds;
wire shift;
wire DEC;

wire w_H;
wire w_T;
wire w_O;
wire w_Z;


lsr_A_res lsr0 ( 
    .clk (clk), .A_bcd (A_bcd), .ones_comp2 (w_ones_comp2), .tens_comp2 (w_tens_comp2), .hundreds_comp2 (w_hundreds_comp2), .LD0 (load_reset), .LD1 (load_ones), .LD2 (load_tens), .LD3 (load_hundreds), .SH (shift), //Entrada
    .bcd_ones (w_bcd_ones), .bcd_tens (w_bcd_tens), .bcd_hundreds (w_bcd_hundreds), .A_bin (A_bin) //Salida
);

comp comp_ones ( .bcd (w_bcd_ones), //Entradas

    .Y (w_O) //Salida
);

comp comp_tens ( .bcd (w_bcd_tens), //Entrada

    .Y (w_T) //Salida
);

comp comp_hundreds ( .bcd (w_bcd_hundreds), //Entrada

    .Y (w_H) //Salida
);

contador_dec cont0 ( .clk (clk), .LD0 (load_reset), .DECI (DEC), //Entrada

    .Z (w_Z) //Salida
);

sum_comp2 sum_comp2_hundreds ( .in_bcd (w_bcd_hundreds), //Entrada
    
    .out_bcd (w_hundreds_comp2) //Salida
);

sum_comp2 sum_comp2_tens ( .in_bcd (w_bcd_tens), //Entrada

    .out_bcd (w_tens_comp2) //Salida
);

sum_comp2 sum_comp2_ones ( .in_bcd (w_bcd_ones), //Entrada

    .out_bcd (w_ones_comp2) //Entrada
);

bin2bcd_control control ( .clk (clk), .init (init), .rst (rst) , .O (w_O), .T (w_T), .H (w_H), .Z (w_Z), //Entradas

    .LD0 (load_reset), .LD1 (load_ones), .LD2 (load_tens), .LD3 (load_hundreds), .SH (shift), .DEC (DEC), .done(done) //Salidas
);



endmodule

Calculadora/rtl/cores/bcd2bin/bcd2bin_TB.v
`timescale 10ns / 10ns
`define SIMULATION

module bcd2bin_TB;


reg clk;
reg init; 
reg rst;
reg [11:0] A_bcd;

wire [7:0] A_bin;
wire done;

// Inicialización del modulo

bcd2bin_top uut ( //Unit under test
    .clk (clk), .init (init), .rst (rst), .A_bcd (A_bcd), // Entradas

    .A_bin (A_bin), .done (done) // Salidas
    
    );





initial clk = 0; 
always #1 clk = ~clk;


initial begin
    $dumpfile("bcd2bin_TB.vcd");
    $dumpvars(-1, bcd2bin_TB);

    $monitor("t=%0t A_bcd=0x%h A_bin=0x%h done=%b", $time, A_bcd, A_bin, done);
end


initial begin

    @(negedge clk);
    @(posedge clk);

    A_bcd = 0;
    init = 0;
    rst = 0;

    @(negedge clk);
    @(posedge clk);

    A_bcd = 12'b001001000011 ; //243

    @(negedge clk);
    @(posedge clk);

    rst = 1;

    @(negedge clk);
    @(posedge clk);

    rst = 0;

    @(negedge clk);
    @(posedge clk);
    
    init = 1;

    @(negedge clk);
    @(posedge clk);

    init = 0;

    wait(done == 1);
    #1000;

    $finish;
end



endmodule

Calculadora/rtl/cores/bcd2bin/bcd2bin_TB.vcd
$date
	Wed Jun  3 12:19:56 2026
$end
$version
	Icarus Verilog
$end
$timescale
	10ns
$end
$scope module bcd2bin_TB $end
$var wire 1 ! done $end
$var wire 8 " A_bin [7:0] $end
$var reg 12 # A_bcd [11:0] $end
$var reg 1 $ clk $end
$var reg 1 % init $end
$var reg 1 & rst $end
$scope module uut $end
$var wire 12 ' A_bcd [11:0] $end
$var wire 1 $ clk $end
$var wire 1 % init $end
$var wire 1 & rst $end
$var wire 4 ( w_tens_comp2 [3:0] $end
$var wire 4 ) w_ones_comp2 [3:0] $end
$var wire 4 * w_hundreds_comp2 [3:0] $end
$var wire 4 + w_bcd_tens [3:0] $end
$var wire 4 , w_bcd_ones [3:0] $end
$var wire 4 - w_bcd_hundreds [3:0] $end
$var wire 1 . w_Z $end
$var wire 1 / w_T $end
$var wire 1 0 w_O $end
$var wire 1 1 w_H $end
$var wire 1 2 shift $end
$var wire 1 3 load_tens $end
$var wire 1 4 load_reset $end
$var wire 1 5 load_ones $end
$var wire 1 6 load_hundreds $end
$var wire 1 ! done $end
$var wire 1 7 DEC $end
$var wire 8 8 A_bin [7:0] $end
$scope module comp_hundreds $end
$var wire 4 9 bcd [3:0] $end
$var reg 1 1 Y $end
$upscope $end
$scope module comp_ones $end
$var wire 4 : bcd [3:0] $end
$var reg 1 0 Y $end
$upscope $end
$scope module comp_tens $end
$var wire 4 ; bcd [3:0] $end
$var reg 1 / Y $end
$upscope $end
$scope module cont0 $end
$var wire 1 $ clk $end
$var wire 1 4 LD0 $end
$var wire 1 7 DECI $end
$var reg 1 . Z $end
$var reg 8 < out [7:0] $end
$upscope $end
$scope module control $end
$var wire 1 1 H $end
$var wire 1 0 O $end
$var wire 1 / T $end
$var wire 1 . Z $end
$var wire 1 $ clk $end
$var wire 1 % init $end
$var wire 1 & rst $end
$var parameter 4 = CHECK $end
$var parameter 4 > DEC_I $end
$var parameter 4 ? FCHECK $end
$var parameter 4 @ FINISH $end
$var parameter 4 A LOAD_H $end
$var parameter 4 B LOAD_O $end
$var parameter 4 C LOAD_T $end
$var parameter 4 D SHIFT $end
$var parameter 4 E START $end
$var reg 1 7 DEC $end
$var reg 1 4 LD0 $end
$var reg 1 5 LD1 $end
$var reg 1 3 LD2 $end
$var reg 1 6 LD3 $end
$var reg 1 2 SH $end
$var reg 5 F count [4:0] $end
$var reg 4 G current_state [3:0] $end
$var reg 1 ! done $end
$var reg 320 H state_name [320:1] $end
$upscope $end
$scope module lsr0 $end
$var wire 12 I A_bcd [11:0] $end
$var wire 1 4 LD0 $end
$var wire 1 5 LD1 $end
$var wire 1 3 LD2 $end
$var wire 1 6 LD3 $end
$var wire 1 2 SH $end
$var wire 1 $ clk $end
$var wire 4 J tens_comp2 [3:0] $end
$var wire 4 K ones_comp2 [3:0] $end
$var wire 4 L hundreds_comp2 [3:0] $end
$var reg 8 M A_bin [7:0] $end
$var reg 4 N bcd_hundreds [3:0] $end
$var reg 4 O bcd_ones [3:0] $end
$var reg 4 P bcd_tens [3:0] $end
$var reg 12 Q temp_A_bcd [11:0] $end
$upscope $end
$scope module sum_comp2_hundreds $end
$var wire 4 R in_bcd [3:0] $end
$var reg 4 S out_bcd [3:0] $end
$upscope $end
$scope module sum_comp2_ones $end
$var wire 4 T in_bcd [3:0] $end
$var reg 4 U out_bcd [3:0] $end
$upscope $end
$scope module sum_comp2_tens $end
$var wire 4 V in_bcd [3:0] $end
$var reg 4 W out_bcd [3:0] $end
$upscope $end
$upscope $end
$upscope $end
$enddefinitions $end
$comment Show the parameter values. $end
$dumpall
b0 E
b1 D
b100 C
b11 B
b101 A
b1000 @
b111 ?
b110 >
b10 =
$end
#0
$dumpvars
bx W
bx V
bx U
bx T
bx S
bx R
bx Q
bx P
bx O
bx N
bx M
bx L
bx K
bx J
bx I
b101001101010100010000010101001001010100 H
b0 G
bx F
bx <
bx ;
bx :
bx 9
bx 8
07
06
05
14
03
02
x1
x0
x/
x.
bx -
bx ,
bx +
bx *
bx )
bx (
bx '
x&
x%
0$
bx #
bx "
0!
$end
#1
b1000 <
b0 "
b0 8
b0 M
1$
#2
0$
#3
b1101 *
b1101 L
b1101 S
01
b1101 (
b1101 J
b1101 W
0/
b1101 )
b1101 K
b1101 U
00
0.
b0 -
b0 9
b0 N
b0 R
b0 +
b0 ;
b0 P
b0 V
b0 ,
b0 :
b0 O
b0 T
b0 Q
0&
0%
b0 #
b0 '
b0 I
1$
#4
0$
#5
b1111 *
b1111 L
b1111 S
b1 (
b1 J
b1 W
b0 )
b0 K
b0 U
b10 -
b10 9
b10 N
b10 R
b100 +
b100 ;
b100 P
b100 V
b11 ,
b11 :
b11 O
b11 T
b1001000011 Q
b1001000011 #
b1001000011 '
b1001000011 I
1$
#6
0$
#7
1&
1$
#8
0$
#9
0&
1$
#10
0$
#11
1%
1$
#12
12
04
b101001101001000010010010100011001010100 H
b0 F
b1 G
0$
#13
b1110 *
b1110 L
b1110 S
b1111 (
b1111 J
b1111 W
b1110 )
b1110 K
b1110 U
b1 -
b1 9
b1 N
b1 R
b10 +
b10 ;
b10 P
b10 V
b1 ,
b1 :
b1 O
b1 T
b100100001 Q
b10000000 "
b10000000 8
b10000000 M
0%
1$
#14
02
b100001101001000010001010100001101001011 H
b10 G
0$
#15
1$
#16
17
b100010001000101010000110101111101001001 H
b110 G
0$
#17
b111 <
1$
#18
07
b10001100100001101001000010001010100001101001011 H
b111 G
0$
#19
1$
#20
12
b101001101001000010010010100011001010100 H
b1 G
0$
#21
b1101 *
b1101 L
b1101 S
1/
b110 (
b110 J
b110 W
b1101 )
b1101 K
b1101 U
b0 -
b0 9
b0 N
b0 R
b1001 +
b1001 ;
b1001 P
b1001 V
b0 ,
b0 :
b0 O
b0 T
b10010000 Q
b11000000 "
b11000000 8
b11000000 M
1$
#22
02
b100001101001000010001010100001101001011 H
b10 G
0$
#23
1$
#24
13
b10011000100111101000001010001000101111101010100 H
b100 G
0$
#25
b11 (
b11 J
b11 W
0/
b110 +
b110 ;
b110 P
b110 V
b1100000 Q
1$
#26
17
03
b100010001000101010000110101111101001001 H
b110 G
0$
#27
b110 <
1$
#28
07
b10001100100001101001000010001010100001101001011 H
b111 G
0$
#29
1$
#30
12
b101001101001000010010010100011001010100 H
b1 G
0$
#31
b0 (
b0 J
b0 W
b11 +
b11 ;
b11 P
b11 V
b110000 Q
b1100000 "
b1100000 8
b1100000 M
1$
#32
02
b100001101001000010001010100001101001011 H
b10 G
0$
#33
1$
#34
17
b100010001000101010000110101111101001001 H
b110 G
0$
#35
b101 <
1$
#36
07
b10001100100001101001000010001010100001101001011 H
b111 G
0$
#37
1$
#38
12
b101001101001000010010010100011001010100 H
b1 G
0$
#39
b1110 (
b1110 J
b1110 W
b101 )
b101 K
b101 U
10
b1 +
b1 ;
b1 P
b1 V
b1000 ,
b1000 :
b1000 O
b1000 T
b11000 Q
b110000 "
b110000 8
b110000 M
1$
#40
02
b100001101001000010001010100001101001011 H
b10 G
0$
#41
1$
#42
15
b10011000100111101000001010001000101111101001111 H
b11 G
0$
#43
00
b10 )
b10 K
b10 U
b101 ,
b101 :
b101 O
b101 T
b10101 Q
1$
#44
17
05
b100010001000101010000110101111101001001 H
b110 G
0$
#45
b100 <
1$
#46
07
b10001100100001101001000010001010100001101001011 H
b111 G
0$
#47
1$
#48
12
b101001101001000010010010100011001010100 H
b1 G
0$
#49
b1101 (
b1101 J
b1101 W
b111 )
b111 K
b111 U
10
b0 +
b0 ;
b0 P
b0 V
b1010 ,
b1010 :
b1010 O
b1010 T
b1010 Q
b10011000 "
b10011000 8
b10011000 M
1$
#50
02
b100001101001000010001010100001101001011 H
b10 G
0$
#51
1$
#52
15
b10011000100111101000001010001000101111101001111 H
b11 G
0$
#53
00
b100 )
b100 K
b100 U
b111 ,
b111 :
b111 O
b111 T
b111 Q
1$
#54
17
05
b100010001000101010000110101111101001001 H
b110 G
0$
#55
b11 <
1$
#56
07
b10001100100001101001000010001010100001101001011 H
b111 G
0$
#57
1$
#58
12
b101001101001000010010010100011001010100 H
b1 G
0$
#59
b0 )
b0 K
b0 U
b11 ,
b11 :
b11 O
b11 T
b11 Q
b11001100 "
b11001100 8
b11001100 M
1$
#60
02
b100001101001000010001010100001101001011 H
b10 G
0$
#61
1$
#62
17
b100010001000101010000110101111101001001 H
b110 G
0$
#63
b10 <
1$
#64
07
b10001100100001101001000010001010100001101001011 H
b111 G
0$
#65
1$
#66
12
b101001101001000010010010100011001010100 H
b1 G
0$
#67
b1110 )
b1110 K
b1110 U
b1 ,
b1 :
b1 O
b1 T
b1 Q
b11100110 "
b11100110 8
b11100110 M
1$
#68
02
b100001101001000010001010100001101001011 H
b10 G
0$
#69
1$
#70
17
b100010001000101010000110101111101001001 H
b110 G
0$
#71
b1 <
1$
#72
07
b10001100100001101001000010001010100001101001011 H
b111 G
0$
#73
1$
#74
12
b101001101001000010010010100011001010100 H
b1 G
0$
#75
b1101 )
b1101 K
b1101 U
b0 ,
b0 :
b0 O
b0 T
b0 Q
b11110011 "
b11110011 8
b11110011 M
1$
#76
02
b100001101001000010001010100001101001011 H
b10 G
0$
#77
1$
#78
17
b100010001000101010000110101111101001001 H
b110 G
0$
#79
b0 <
1$
#80
07
b10001100100001101001000010001010100001101001011 H
b111 G
0$
#81
1.
1$
#82
1!
b10001100100100101001110010010010101001101001000 H
b1000 G
0$
#83
1$
#84
b1 F
0$
#85
1$
#86
b10 F
0$
#87
1$
#88
b11 F
0$
#89
1$
#90
b100 F
0$
#91
1$
#92
b101 F
0$
#93
1$
#94
b110 F
0$
#95
1$
#96
b111 F
0$
#97
1$
#98
b1000 F
0$
#99
1$
#100
b1001 F
0$
#101
1$
#102
b1010 F
0$
#103
1$
#104
b1011 F
0$
#105
1$
#106
b1100 F
0$
#107
1$
#108
b1101 F
0$
#109
1$
#110
b1110 F
0$
#111
1$
#112
b1111 F
0$
#113
1$
#114
b10000 F
0$
#115
1$
#116
b10001 F
0$
#117
1$
#118
b10010 F
0$
#119
1$
#120
b10011 F
0$
#121
1$
#122
b10100 F
0$
#123
1$
#124
b10101 F
0$
#125
1$
#126
b10110 F
0$
#127
1$
#128
b10111 F
0$
#129
1$
#130
b11000 F
0$
#131
1$
#132
b11001 F
0$
#133
1$
#134
b11010 F
0$
#135
1$
#136
b11011 F
0$
#137
1$
#138
b11100 F
0$
#139
1$
#140
0!
14
b101001101010100010000010101001001010100 H
b0 G
b11101 F
0$
#141
b1000 <
b1111 *
b1111 L
b1111 S
b1 (
b1 J
b1 W
b0 )
b0 K
b0 U
b10 -
b10 9
b10 N
b10 R
b100 +
b100 ;
b100 P
b100 V
b11 ,
b11 :
b11 O
b11 T
b1001000011 Q
b0 "
b0 8
b0 M
1$
#142
0$
#143
0.
1$
